{
  "TITLE": "Episode 84 - Corn-Fed Anarchy (featuring Iowancap) [Adult Language]",
  "NUMBER": 84,
  "DESCRIPTION": "This week, we're talking to a friend of the show and a youth pastoring anarchist out of the fine state of Iowa. One of the three hosts of the Flyover Libertarian Podcast, Josh (a.k.a. Iowancap), joins us to talk about Christianity, anarchy, and the world we currently live in.",
  "CONTENT": "This week, we're talking to a friend of the show and a youth pastoring anarchist out of the fine state of Iowa. One of the three hosts of the Flyover Libertarian Podcast, Josh (a.k.a. Iowancap), joins us to talk about Christianity, anarchy, and the world we currently live in.",
  "IMAGE": "tmo_0084.png",
  "ITUNES_IMAGE": "tmo_0084.png",
  "FILE": "tmo_0084.mp3",
  "DATE": "2021-04-07T01:01:21.206Z",
  "EXPLICIT": true
}
