{
  "TITLE": "Episode 118 - Peering Through The Veil with Kate Cherrell",
  "NUMBER": 118,
  "DESCRIPTION": "This week, our friend Kate from Burials and Beyond comes back to educate us about her speciality, Gothic Spiritualism. With a PhD in the subject, Kate is a wealth of knowledge. Join us to learn about how our ancestors attempted communication with the dead.",
  "CONTENT": "This week, our friend Kate from Burials and Beyond comes back to educate us about her speciality, Gothic Spiritualism. With a PhD in the subject, Kate is a wealth of knowledge. Join us to learn about how our ancestors attempted communication with the dead.",
  "IMAGE": "tmo_0118.png",
  "ITUNES_IMAGE": "tmo_0118.png",
  "FILE": "tmo_0118.mp3",
  "DATE": "2021-11-17T20:30:47.206Z",
  "EXPLICIT": false
}
