{
  "TITLE": "Episode 38 - Bat Butthole Soup",
  "NUMBER": 38,
  "DESCRIPTION": "This week, we talk about how the Senate in Virginia dgaf about your gun protests, Assange's lack of human rights, bat butthole soup, protests in Baghdad, Brexit's status, the Doomsday clock, impeachment, the democratic race for the presidency, and Joe Rogan saying the n-word.",
  "CONTENT": "This week, we talk about how the Senate in Virginia dgaf about your gun protests, Assange's lack of human rights, bat butthole soup, protests in Baghdad, Brexit's status, the Doomsday clock, impeachment, the democratic race for the presidency, and Joe Rogan saying the n-word.",
  "IMAGE": "mlga_0038.png",
  "ITUNES_IMAGE": "mlga_0038.png",
  "FILE": "mlga_0038.mp3",
  "DATE": "2020-01-27T11:09:25.206Z",
  "EXPLICIT": true
}
